<?xml version="1.0" encoding="UTF-8"?>
<objects serializationModel="Studio.02.02.00">
	<object class="AudioFile" id="{7a8b6542-3b62-4af8-b8bd-e152afd4c98b}">
		<property name="assetPath">
			<value>Voz/Passaro1/VOZ_PASSARO1_Blablacao1.wav</value>
		</property>
		<property name="frequencyInKHz">
			<value>48</value>
		</property>
		<property name="channelCount">
			<value>2</value>
		</property>
		<property name="length">
			<value>4</value>
		</property>
		<relationship name="masterAssetFolder">
			<destination>{88cfcb49-5c8c-41bf-8472-6b2e885f8452}</destination>
		</relationship>
	</object>
</objects>
