<?xml version="1.0" encoding="UTF-8"?>
<objects serializationModel="Studio.02.02.00">
	<object class="AudioFile" id="{f20c2f63-d44e-4e5b-8383-b506a6448018}">
		<property name="assetPath">
			<value>Respostas/RESPOSTA3_RespostaRuim.wav</value>
		</property>
		<property name="frequencyInKHz">
			<value>48</value>
		</property>
		<property name="channelCount">
			<value>2</value>
		</property>
		<property name="length">
			<value>2.8321458333333331</value>
		</property>
		<relationship name="masterAssetFolder">
			<destination>{88cfcb49-5c8c-41bf-8472-6b2e885f8452}</destination>
		</relationship>
	</object>
</objects>
